empyrical/__init__.py
empyrical/_version.py
empyrical/perf_attrib.py
empyrical/periods.py
empyrical/stats.py
empyrical/utils.py
empyrical/tests/__init__.py
empyrical/tests/test_perf_attrib.py
empyrical/tests/test_stats.py
empyrical-0.4.2.dist-info/DESCRIPTION.rst
empyrical-0.4.2.dist-info/METADATA
empyrical-0.4.2.dist-info/RECORD
empyrical-0.4.2.dist-info/WHEEL
empyrical-0.4.2.dist-info/metadata.json
empyrical-0.4.2.dist-info/top_level.txt
